crashsense/__init__.py
crashsense/cli.py
crashsense/config.py
crashsense/tui.py
crashsense/utils.py
crashsense/core/analyzer.py
crashsense/core/k8s_monitor.py
crashsense/core/llm_adapter.py
crashsense/core/memory.py
crashsense/core/prometheus_collector.py
crashsense/core/remediation.py
data/crashsense_best_practices.md
data/kubernetes_remediation_playbook.md
data/linux_permission_paths.md
data/python_exceptions_playbook.md
data/web_server_error_patterns.md
crashsense-2.0.0.dist-info/LICENSE
crashsense-2.0.0.dist-info/METADATA
crashsense-2.0.0.dist-info/WHEEL
crashsense-2.0.0.dist-info/entry_points.txt
crashsense-2.0.0.dist-info/top_level.txt
crashsense-2.0.0.dist-info/RECORD
