Metadata-Version: 2.1
Name: crashsense
Version: 2.0.0
Summary: Self-Healing Kubernetes Platform - AI-powered crash detection and automated remediation for containerized workloads
Author-email: Mohamed Aziz Bahloul <azizbahloul3@gmail.com>
Project-URL: Homepage, https://github.com/AzizBahloul/CrashSense
Project-URL: Documentation, https://github.com/AzizBahloul/CrashSense#readme
Project-URL: Repository, https://github.com/AzizBahloul/CrashSense.git
Project-URL: Issues, https://github.com/AzizBahloul/CrashSense/issues
Keywords: kubernetes,monitoring,self-healing,crash-detection,remediation,devops,sre,prometheus
Classifier: Development Status :: 4 - Beta
Classifier: Intended Audience :: Developers
Classifier: Intended Audience :: System Administrators
Classifier: Topic :: System :: Monitoring
Classifier: Topic :: System :: Systems Administration
Classifier: Programming Language :: Python :: 3
Classifier: Programming Language :: Python :: 3.8
Classifier: Programming Language :: Python :: 3.9
Classifier: Programming Language :: Python :: 3.10
Classifier: Programming Language :: Python :: 3.11
Classifier: Programming Language :: Python :: 3.12
Requires-Python: >=3.8
License-File: LICENSE
Requires-Dist: click>=8.0
Requires-Dist: rich>=12.0
Requires-Dist: sqlalchemy>=1.4
Requires-Dist: python-dotenv>=0.21
Requires-Dist: keyring>=23.0
Requires-Dist: cryptography>=39.0
Requires-Dist: requests>=2.28
Requires-Dist: tabulate>=0.9
Requires-Dist: toml>=0.10
Requires-Dist: kubernetes>=28.0.0
Requires-Dist: prometheus-client>=0.19.0
Requires-Dist: prometheus-api-client>=0.5.5
Requires-Dist: pyyaml>=6.0
Requires-Dist: psutil>=5.9.0
Requires-Dist: flask>=3.0.0
Provides-Extra: dev
Requires-Dist: pytest>=7.4.0; extra == "dev"
Requires-Dist: pytest-cov>=4.1.0; extra == "dev"
Requires-Dist: pytest-mock>=3.12.0; extra == "dev"
Requires-Dist: black>=23.0.0; extra == "dev"
Requires-Dist: flake8>=6.0.0; extra == "dev"
Requires-Dist: mypy>=1.0.0; extra == "dev"
